odoo/addons/crm_lead_firstname/README.rst
odoo/addons/crm_lead_firstname/__init__.py
odoo/addons/crm_lead_firstname/__manifest__.py
odoo/addons/crm_lead_firstname/i18n/bg.po
odoo/addons/crm_lead_firstname/i18n/crm_lead_firstname.pot
odoo/addons/crm_lead_firstname/i18n/de.po
odoo/addons/crm_lead_firstname/i18n/es.po
odoo/addons/crm_lead_firstname/i18n/es_AR.po
odoo/addons/crm_lead_firstname/i18n/fr.po
odoo/addons/crm_lead_firstname/i18n/fr_CH.po
odoo/addons/crm_lead_firstname/i18n/hr.po
odoo/addons/crm_lead_firstname/i18n/it.po
odoo/addons/crm_lead_firstname/i18n/pt_BR.po
odoo/addons/crm_lead_firstname/i18n/sk.po
odoo/addons/crm_lead_firstname/i18n/sl.po
odoo/addons/crm_lead_firstname/i18n/tr.po
odoo/addons/crm_lead_firstname/i18n/zh_CN.po
odoo/addons/crm_lead_firstname/models/__init__.py
odoo/addons/crm_lead_firstname/models/crm_lead.py
odoo/addons/crm_lead_firstname/readme/CONTRIBUTORS.rst
odoo/addons/crm_lead_firstname/readme/DESCRIPTION.rst
odoo/addons/crm_lead_firstname/readme/INSTALL.rst
odoo/addons/crm_lead_firstname/readme/USAGE.rst
odoo/addons/crm_lead_firstname/static/description/icon.png
odoo/addons/crm_lead_firstname/static/description/index.html
odoo/addons/crm_lead_firstname/tests/__init__.py
odoo/addons/crm_lead_firstname/tests/test_crm_lead.py
odoo/addons/crm_lead_firstname/views/crm_lead_view.xml
odoo14_addon_crm_lead_firstname-14.0.1.0.2.dist-info/METADATA
odoo14_addon_crm_lead_firstname-14.0.1.0.2.dist-info/WHEEL
odoo14_addon_crm_lead_firstname-14.0.1.0.2.dist-info/top_level.txt
odoo14_addon_crm_lead_firstname-14.0.1.0.2.dist-info/RECORD
