Metadata-Version: 2.1
Name: odoo14-addon-crm-lead-firstname
Version: 14.0.1.0.2
Summary: Specify split names for contacts in leads
Home-page: https://github.com/OCA/crm
Author: Tecnativa, Odoo Community Association (OCA)
Author-email: support@odoo-community.org
License: AGPL-3
Platform: UNKNOWN
Classifier: Programming Language :: Python
Classifier: Framework :: Odoo
Classifier: License :: OSI Approved :: GNU Affero General Public License v3
Requires-Python: >=3.6
Requires-Dist: odoo14-addon-partner-firstname
Requires-Dist: odoo (<14.1dev,>=14.0a)
